enumDatabase/EnumCollections.py
enumDatabase/__init__.py
lbCnae/LbCnae.py
lbCnae/__init__.py
lbCompanies/LbCompanies.py
lbCompanies/__init__.py
lbConnection/LbConnection.py
lbConnection/Projection.py
lbConnection/Query.py
lbConnection/__init__.py
lbCounty/LbCounty.py
lbCounty/__init__.py
lbMenu/LbMenu.py
lbMenu/__init__.py
lbUser/AddressLbUser.py
lbUser/ConfirmationCodeLbUser.py
lbUser/EnumStatusLbUser.py
lbUser/LbUser.py
lbUser/__init__.py
lb_database-1.1.17.dist-info/METADATA
lb_database-1.1.17.dist-info/WHEEL
lb_database-1.1.17.dist-info/top_level.txt
lb_database-1.1.17.dist-info/RECORD
