Metadata-Version: 2.1
Name: lb-database
Version: 1.1.17
Summary: Library with data models by lb services
Author: Lucas Barros
Author-email: lucasbarros2000@hotmail.com
Classifier: Programming Language :: Python :: 3.6
Classifier: License :: OSI Approved :: MIT License
Classifier: Operating System :: OS Independent
Requires-Python: >=3.6
